pyrepo/__init__.py
pyrepo/commands.py
pyrepo/hosts.py
pyrepo/repo.py
pyrepo/version.py
pyrepo-0.1.2.dist-info/DESCRIPTION.rst
pyrepo-0.1.2.dist-info/METADATA
pyrepo-0.1.2.dist-info/metadata.json
pyrepo-0.1.2.dist-info/RECORD
pyrepo-0.1.2.dist-info/top_level.txt
pyrepo-0.1.2.dist-info/WHEEL
