Metadata-Version: 2.0
Name: pyrepo
Version: 0.1.2
Summary: Python repository abstraction
Home-page: https://github.com/dghubble/pyrepo
Author: Dalton Hubble
Author-email: dghubble@gmail.com
License: MIT
Keywords: repo repository vcs git mercurial hg svn subversion bazaar
Platform: UNKNOWN
Classifier: Development Status :: 3 - Alpha
Classifier: Intended Audience :: Developers
Classifier: Topic :: Software Development :: Build Tools
Classifier: License :: OSI Approved :: MIT License
Classifier: Programming Language :: Python :: 2
Classifier: Programming Language :: Python :: 2.6
Classifier: Programming Language :: Python :: 2.7
Classifier: Programming Language :: Python :: 3
Classifier: Programming Language :: Python :: 3.1
Classifier: Programming Language :: Python :: 3.2
Classifier: Programming Language :: Python :: 3.3
Classifier: Programming Language :: Python :: 3.4
